data_records/__init__.py
data_records/code_generation.py
data_records/coerce_types.py
data_records/exceptions.py
data_records/field.py
data_records/record.py
data_records/utilities.py
data_records-0.4.2.dist-info/LICENSE
data_records-0.4.2.dist-info/METADATA
data_records-0.4.2.dist-info/WHEEL
data_records-0.4.2.dist-info/top_level.txt
data_records-0.4.2.dist-info/RECORD
